histomics/._LICENSE
histomics/._README.md
histomics/.___init__.py
histomics/._get_histomics_features.py
histomics/LICENSE
histomics/README.md
histomics/__init__.py
histomics/get_histomics_features.py
histomics-0.0.1.dist-info/METADATA
histomics-0.0.1.dist-info/WHEEL
histomics-0.0.1.dist-info/RECORD
