Metadata-Version: 2.1
Name: histomics
Version: 0.0.1
Summary: Histomics slide(WSI) analysis toolkit
Author: ScienceAdvances
Author-email: yehior@hotmail.com
Requires-Python: >=3.10,<4.0
Classifier: Programming Language :: Python :: 3
Classifier: Programming Language :: Python :: 3.10
Classifier: Programming Language :: Python :: 3.11
Classifier: Programming Language :: Python :: 3.12
